chord_matrix/__init__.py
chord_matrix/main.py
chord_matrix-0.1.1.dist-info/LICENSE
chord_matrix-0.1.1.dist-info/METADATA
chord_matrix-0.1.1.dist-info/WHEEL
chord_matrix-0.1.1.dist-info/entry_points.txt
chord_matrix-0.1.1.dist-info/top_level.txt
chord_matrix-0.1.1.dist-info/RECORD
