Metadata-Version: 2.1
Name: chord-matrix
Version: 0.1.1
Summary: A package to generate a matrix for chord diagrams
Home-page: https://github.com/Habibnasir23/chord_matrix
Author: Habib Nasir
Author-email: habibnasir23@gmail.com
Classifier: Programming Language :: Python :: 3
Classifier: License :: OSI Approved :: MIT License
Classifier: Operating System :: OS Independent
Requires-Python: >=3.6
License-File: LICENSE
Requires-Dist: pandas
Requires-Dist: numpy
